pyreaqtive/__init__.py
pyreaqtive/py.typed
pyreaqtive/rq_async.py
pyreaqtive/rq_connect.py
pyreaqtive/rq_getattr.py
pyreaqtive/rq_getlist.py
pyreaqtive/layouts/__init__.py
pyreaqtive/layouts/rqboxlayout.py
pyreaqtive/layouts/rqhboxlayout.py
pyreaqtive/layouts/rqvboxlayout.py
pyreaqtive/models/__init__.py
pyreaqtive/models/rqbool.py
pyreaqtive/models/rqchoice.py
pyreaqtive/models/rqfloat.py
pyreaqtive/models/rqint.py
pyreaqtive/models/rqlist.py
pyreaqtive/models/rqmodel.py
pyreaqtive/models/rqobject.py
pyreaqtive/models/rqtext.py
pyreaqtive/models/sequence_matching.py
pyreaqtive/widgets/__init__.py
pyreaqtive/widgets/rqcheckbox.py
pyreaqtive/widgets/rqcombobox.py
pyreaqtive/widgets/rqdial.py
pyreaqtive/widgets/rqdoublespinbox.py
pyreaqtive/widgets/rqlabel.py
pyreaqtive/widgets/rqlineedit.py
pyreaqtive/widgets/rqprogressbar.py
pyreaqtive/widgets/rqpushbutton.py
pyreaqtive/widgets/rqslider.py
pyreaqtive/widgets/rqspinbox.py
pyreaqtive/widgets/rqwidget.py
pyreaqtive/widgets/rqwidgetobject.py
pyreaqtive-1.4.4.dist-info/LICENSE
pyreaqtive-1.4.4.dist-info/METADATA
pyreaqtive-1.4.4.dist-info/WHEEL
pyreaqtive-1.4.4.dist-info/top_level.txt
pyreaqtive-1.4.4.dist-info/RECORD
