Metadata-Version: 2.1
Name: pyreaqtive
Version: 1.4.4
Summary: PyQt Reactive Framework
Home-page: https://github.com/polfeliu/pyreaqtive
Author: Pol Feliu Cuberes
Author-email: feliupol@gmail.com
License: Attribution-NoDerivatives 4.0 International (CC BY-ND 4.0)
Keywords: pyqt5 framework reactive gui
License-File: LICENSE
Requires-Dist: qtpy (>2.0.0)
